statspedia/__init__.py
statspedia/errors.py
statspedia/wiki_stream.py
statspedia-0.2.0.dist-info/licenses/LICENSE
statspedia-0.2.0.dist-info/METADATA
statspedia-0.2.0.dist-info/WHEEL
statspedia-0.2.0.dist-info/top_level.txt
statspedia-0.2.0.dist-info/RECORD
