Metadata-Version: 2.4
Name: statspedia
Version: 0.2.0
Summary: A package to process data from Wikimedia using the server sent events (SSE) protocol.
Author-email: John Glauber <johnbglauber@gmail.com>
Project-URL: Homepage, https://github.com/jglauber/wikipediastats
Project-URL: Issues, https://github.com/jglauber/wikipediastats/issues
Classifier: Programming Language :: Python :: 3
Classifier: Operating System :: OS Independent
Requires-Python: >=3.8
License-File: LICENSE
Requires-Dist: aiohappyeyeballs==2.6.1
Requires-Dist: aiohttp==3.11.13
Requires-Dist: aiosignal==1.3.2
Requires-Dist: anyio==4.9.0
Requires-Dist: attrs==25.3.0
Requires-Dist: certifi==2025.4.26
Requires-Dist: dnspython==2.7.0
Requires-Dist: frozenlist==1.6.0
Requires-Dist: h11==0.16.0
Requires-Dist: httpcore==1.0.9
Requires-Dist: idna==3.10
Requires-Dist: multidict==6.4.4
Requires-Dist: propcache==0.3.1
Requires-Dist: pymongo==4.13.0
Requires-Dist: sniffio==1.3.1
Requires-Dist: yarl==1.20.0
Dynamic: license-file
